spanconsumer/__init__.py
spanconsumer/_configuration.py
spanconsumer/_consumer.py
spanconsumer/_errors.py
spanconsumer/_incoming_outgoing.py
spanconsumer/_scribe.py
spanconsumer/_test_client.py
spanconsumer/_types.py
spanconsumer/_version.py
spanconsumer-0.3.3.dist-info/LICENSE
spanconsumer-0.3.3.dist-info/METADATA
spanconsumer-0.3.3.dist-info/WHEEL
spanconsumer-0.3.3.dist-info/top_level.txt
spanconsumer-0.3.3.dist-info/RECORD
